{
	"id": "03-01/65",
	"date": "03.01.25",
	"address": "ул. Ленина, 45",
	"status": "done",
	"client": {
		"name": "Иванов И.И.",
		"phone": "+7 (999) 123-45-67"
	},
	"yourOutlay": {
		"items": [
			{
				"id": 0,
				"name": "Такси",
				"money": {
					"value": 1750,
					"currency": "RUB"
				}
			},
			{
				"id": 1,
				"name": "Автобус",
				"money": {
					"value": 0,
					"currency": "RUB"
				}
			},
			{
				"id": 2,
				"name": "Еда",
				"money": {
					"value": 850,
					"currency": "RUB"
				}
			},
			{
				"id": 3,
				"name": "ЗЧ свои",
				"money": {
					"value": 780,
					"currency": "RUB"
				}
			}
		],
		"rest": {
			"name": "Иное",
			"money": {
				"value": 0,
				"currency": "RUB"
			}
		},
		"varranty": {
			"name": "Гарантия",
			"money": {
				"value": 0,
				"currency": "RUB"
			}
		},
		"yourTotal": {
			"before": {
				"value": 3380,
				"currency": "RUB"
			},
			"after": {
				"value": 3600,
				"currency": "RUB"
			}
		}
	},
	"income": {
		"items": [
			{
				"id": 0,
				"name": "Залог",
				"money": {
					"value": 2000,
					"sign": true,
					"currency": "RUB"
				},
				"payStatus": "part"
			},
			{
				"id": 1,
				"name": "Фирма",
				"money": {
					"value": 15000,
					"sign": true,
					"currency": "RUB"
				},
				"payStatus": "full"
			},
			{
				"id": 2,
				"name": "ЗЧ офис",
				"money": {
					"value": 4800,
					"sign": false,
					"currency": "RUB"
				}
			}
		],
		"outlay": {
			"name": "Расходка",
			"money": {
				"value": 700,
				"sign": true,
				"currency": "RUB"
			}
		},
		"summary": [
			{
				"id": 0,
				"name": "Фирма итого",
				"money": {
					"value": 17000,
					"currency": "RUB"
				}
			},
			{
				"id": 1,
				"name": "Чаевые (от фирмы)",
				"money": {
					"value": 500,
					"currency": "RUB"
				}
			},
			{
				"id": 2,
				"name": "Доплата (клиент)",
				"money": {
					"value": 1000,
					"currency": "RUB"
				}
			},
			{
				"id": 3,
				"name": "Добро (сам)",
				"money": {
					"value": 800,
					"currency": "RUB"
				}
			}
		]
	},
	"pass": {
		"val": {
			"value": 11500,
			"currency": "RUB"
		},
		"toPass": {
			"value": 9200,
			"currency": "RUB"
		},
		"sallaryNextMonth": {
			"value": 2300,
			"currency": "RUB",
			"sign": true
		},
		"yourCurrentIncome": {
			"value": 2300,
			"currency": "RUB"
		},
		"yourTotalIncome": {
			"value": 700,
			"currency": "RUB",
			"sign": false
		}
	}
}
